{
  "version": "5",
  "dialect": "sqlite",
  "id": "d91ba333-612f-4b5d-bd48-824c52b9db66",
  "prevId": "fcd22e09-37ba-4a4e-96c1-4b5bcf7aac3e",
  "tables": {
    "account": {
      "name": "account",
      "columns": {
        "userId": {
          "name": "userId",
          "type": "text",
          "primaryKey": false,
          "notNull": true,
          "autoincrement": false
        },
        "type": {
          "name": "type",
          "type": "text",
          "primaryKey": false,
          "notNull": true,
          "autoincrement": false
        },
        "provider": {
          "name": "provider",
          "type": "text",
          "primaryKey": false,
          "notNull": true,
          "autoincrement": false
        },
        "providerAccountId": {
          "name": "providerAccountId",
          "type": "text",
          "primaryKey": false,
          "notNull": true,
          "autoincrement": false
        },
        "refresh_token": {
          "name": "refresh_token",
          "type": "text",
          "primaryKey": false,
          "notNull": false,
          "autoincrement": false
        },
        "access_token": {
          "name": "access_token",
          "type": "text",
          "primaryKey": false,
          "notNull": false,
          "autoincrement": false
        },
        "expires_at": {
          "name": "expires_at",
          "type": "integer",
          "primaryKey": false,
          "notNull": false,
          "autoincrement": false
        },
        "token_type": {
          "name": "token_type",
          "type": "text",
          "primaryKey": false,
          "notNull": false,
          "autoincrement": false
        },
        "scope": {
          "name": "scope",
          "type": "text",
          "primaryKey": false,
          "notNull": false,
          "autoincrement": false
        },
        "id_token": {
          "name": "id_token",
          "type": "text",
          "primaryKey": false,
          "notNull": false,
          "autoincrement": false
        },
        "session_state": {
          "name": "session_state",
          "type": "text",
          "primaryKey": false,
          "notNull": false,
          "autoincrement": false
        }
      },
      "indexes": {},
      "foreignKeys": {
        "account_userId_user_id_fk": {
          "name": "account_userId_user_id_fk",
          "tableFrom": "account",
          "tableTo": "user",
          "columnsFrom": [
            "userId"
          ],
          "columnsTo": [
            "id"
          ],
          "onDelete": "cascade",
          "onUpdate": "no action"
        }
      },
      "compositePrimaryKeys": {
        "account_provider_providerAccountId_pk": {
          "columns": [
            "provider",
            "providerAccountId"
          ],
          "name": "account_provider_providerAccountId_pk"
        }
      },
      "uniqueConstraints": {}
    },
    "permissions": {
      "name": "permissions",
      "columns": {
        "id": {
          "name": "id",
          "type": "text",
          "primaryKey": true,
          "notNull": true,
          "autoincrement": false
        },
        "name": {
          "name": "name",
          "type": "text",
          "primaryKey": false,
          "notNull": true,
          "autoincrement": false
        },
        "description": {
          "name": "description",
          "type": "text",
          "primaryKey": false,
          "notNull": true,
          "autoincrement": false,
          "default": "''"
        }
      },
      "indexes": {
        "permissions_name_unique": {
          "name": "permissions_name_unique",
          "columns": [
            "name"
          ],
          "isUnique": true
        }
      },
      "foreignKeys": {},
      "compositePrimaryKeys": {},
      "uniqueConstraints": {}
    },
    "role_permissions": {
      "name": "role_permissions",
      "columns": {
        "id": {
          "name": "id",
          "type": "text",
          "primaryKey": false,
          "notNull": false,
          "autoincrement": false
        }
      },
      "indexes": {},
      "foreignKeys": {
        "role_permissions_id_permissions_id_fk": {
          "name": "role_permissions_id_permissions_id_fk",
          "tableFrom": "role_permissions",
          "tableTo": "permissions",
          "columnsFrom": [
            "id"
          ],
          "columnsTo": [
            "id"
          ],
          "onDelete": "no action",
          "onUpdate": "no action"
        },
        "role_permissions_id_roles_id_fk": {
          "name": "role_permissions_id_roles_id_fk",
          "tableFrom": "role_permissions",
          "tableTo": "roles",
          "columnsFrom": [
            "id"
          ],
          "columnsTo": [
            "id"
          ],
          "onDelete": "no action",
          "onUpdate": "no action"
        }
      },
      "compositePrimaryKeys": {
        "role_permissions_id_id_pk": {
          "columns": [
            "id",
            "id"
          ],
          "name": "role_permissions_id_id_pk"
        }
      },
      "uniqueConstraints": {}
    },
    "user_roles": {
      "name": "user_roles",
      "columns": {
        "id": {
          "name": "id",
          "type": "text",
          "primaryKey": false,
          "notNull": false,
          "autoincrement": false
        }
      },
      "indexes": {},
      "foreignKeys": {
        "user_roles_id_user_id_fk": {
          "name": "user_roles_id_user_id_fk",
          "tableFrom": "user_roles",
          "tableTo": "user",
          "columnsFrom": [
            "id"
          ],
          "columnsTo": [
            "id"
          ],
          "onDelete": "no action",
          "onUpdate": "no action"
        },
        "user_roles_id_roles_id_fk": {
          "name": "user_roles_id_roles_id_fk",
          "tableFrom": "user_roles",
          "tableTo": "roles",
          "columnsFrom": [
            "id"
          ],
          "columnsTo": [
            "id"
          ],
          "onDelete": "no action",
          "onUpdate": "no action"
        }
      },
      "compositePrimaryKeys": {
        "user_roles_id_id_pk": {
          "columns": [
            "id",
            "id"
          ],
          "name": "user_roles_id_id_pk"
        }
      },
      "uniqueConstraints": {}
    },
    "roles": {
      "name": "roles",
      "columns": {
        "id": {
          "name": "id",
          "type": "text",
          "primaryKey": true,
          "notNull": true,
          "autoincrement": false
        },
        "name": {
          "name": "name",
          "type": "text",
          "primaryKey": false,
          "notNull": true,
          "autoincrement": false
        }
      },
      "indexes": {
        "roles_name_unique": {
          "name": "roles_name_unique",
          "columns": [
            "name"
          ],
          "isUnique": true
        }
      },
      "foreignKeys": {},
      "compositePrimaryKeys": {},
      "uniqueConstraints": {}
    },
    "session": {
      "name": "session",
      "columns": {
        "sessionToken": {
          "name": "sessionToken",
          "type": "text",
          "primaryKey": true,
          "notNull": true,
          "autoincrement": false
        },
        "userId": {
          "name": "userId",
          "type": "text",
          "primaryKey": false,
          "notNull": true,
          "autoincrement": false
        },
        "expires": {
          "name": "expires",
          "type": "integer",
          "primaryKey": false,
          "notNull": true,
          "autoincrement": false
        }
      },
      "indexes": {},
      "foreignKeys": {
        "session_userId_user_id_fk": {
          "name": "session_userId_user_id_fk",
          "tableFrom": "session",
          "tableTo": "user",
          "columnsFrom": [
            "userId"
          ],
          "columnsTo": [
            "id"
          ],
          "onDelete": "cascade",
          "onUpdate": "no action"
        }
      },
      "compositePrimaryKeys": {},
      "uniqueConstraints": {}
    },
    "user": {
      "name": "user",
      "columns": {
        "id": {
          "name": "id",
          "type": "text",
          "primaryKey": true,
          "notNull": true,
          "autoincrement": false
        },
        "name": {
          "name": "name",
          "type": "text",
          "primaryKey": false,
          "notNull": false,
          "autoincrement": false
        },
        "email": {
          "name": "email",
          "type": "text",
          "primaryKey": false,
          "notNull": true,
          "autoincrement": false
        },
        "emailVerified": {
          "name": "emailVerified",
          "type": "integer",
          "primaryKey": false,
          "notNull": false,
          "autoincrement": false
        },
        "image": {
          "name": "image",
          "type": "text",
          "primaryKey": false,
          "notNull": false,
          "autoincrement": false
        }
      },
      "indexes": {},
      "foreignKeys": {},
      "compositePrimaryKeys": {},
      "uniqueConstraints": {}
    },
    "verificationToken": {
      "name": "verificationToken",
      "columns": {
        "identifier": {
          "name": "identifier",
          "type": "text",
          "primaryKey": false,
          "notNull": true,
          "autoincrement": false
        },
        "token": {
          "name": "token",
          "type": "text",
          "primaryKey": false,
          "notNull": true,
          "autoincrement": false
        },
        "expires": {
          "name": "expires",
          "type": "integer",
          "primaryKey": false,
          "notNull": true,
          "autoincrement": false
        }
      },
      "indexes": {},
      "foreignKeys": {},
      "compositePrimaryKeys": {
        "verificationToken_identifier_token_pk": {
          "columns": [
            "identifier",
            "token"
          ],
          "name": "verificationToken_identifier_token_pk"
        }
      },
      "uniqueConstraints": {}
    }
  },
  "enums": {},
  "_meta": {
    "schemas": {},
    "tables": {},
    "columns": {}
  }
}